docc/__init__.py
docc/__main__.py
docc/build.py
docc/cli.py
docc/context.py
docc/discover.py
docc/document.py
docc/performance.py
docc/py.typed
docc/settings.py
docc/source.py
docc/transform.py
docc/plugins/__init__.py
docc/plugins/debug.py
docc/plugins/files.py
docc/plugins/loader.py
docc/plugins/mistletoe.py
docc/plugins/references.py
docc/plugins/resources.py
docc/plugins/search.py
docc/plugins/html/__init__.py
docc/plugins/html/static/docc.css
docc/plugins/html/static/search.js
docc/plugins/html/static/chota/dist/chota.min.css
docc/plugins/html/static/fuse/dist/fuse.min.js
docc/plugins/html/templates/base.html
docc/plugins/html/templates/search.html
docc/plugins/listing/__init__.py
docc/plugins/listing/templates/listing.html
docc/plugins/python/__init__.py
docc/plugins/python/cst.py
docc/plugins/python/html.py
docc/plugins/python/nodes.py
docc/plugins/python/templates/html/access.html
docc/plugins/python/templates/html/attribute.html
docc/plugins/python/templates/html/binary_operation.html
docc/plugins/python/templates/html/bit_or.html
docc/plugins/python/templates/html/class.html
docc/plugins/python/templates/html/function.html
docc/plugins/python/templates/html/list.html
docc/plugins/python/templates/html/module.html
docc/plugins/python/templates/html/name.html
docc/plugins/python/templates/html/parameter.html
docc/plugins/python/templates/html/subscript.html
docc/plugins/python/templates/html/tuple.html
docc/plugins/python/templates/html/type.html
docc/plugins/verbatim/__init__.py
docc/plugins/verbatim/html.py
docc-0.3.0.dist-info/licenses/LICENSE.md
docc-0.3.0.dist-info/METADATA
docc-0.3.0.dist-info/WHEEL
docc-0.3.0.dist-info/entry_points.txt
docc-0.3.0.dist-info/top_level.txt
docc-0.3.0.dist-info/RECORD
